{
  "project_info": {
    "project_number": "632108227199",
    "project_id": "magiccoffee-e0a37",
    "storage_bucket": "magiccoffee-e0a37.appspot.com"
  },
  "client": [
    {
      "client_info": {
        "mobilesdk_app_id": "1:632108227199:android:9fe6961a046e7448e4fd4a",
        "android_client_info": {
          "package_name": "com.example.magiccoffee"
        }
      },
      "oauth_client": [
        {
          "client_id": "632108227199-eve7uepg830ct5gpg3g7lu02hqnfmiml.apps.googleusercontent.com",
          "client_type": 1,
          "android_info": {
            "package_name": "com.example.magiccoffee",
            "certificate_hash": "eb3332a96115f52af2c9bcc4606f120a190edf8b"
          }
        },
        {
          "client_id": "632108227199-knhg6o8vfmmk3hs2f9akdm6jir4i1c46.apps.googleusercontent.com",
          "client_type": 3
        }
      ],
      "api_key": [
        {
          "current_key": "AIzaSyCF7TKXKFWzCViUhPwdOW0LUhcdX6qARfI"
        }
      ],
      "services": {
        "appinvite_service": {
          "other_platform_oauth_client": [
            {
              "client_id": "632108227199-knhg6o8vfmmk3hs2f9akdm6jir4i1c46.apps.googleusercontent.com",
              "client_type": 3
            }
          ]
        }
      }
    }
  ],
  "configuration_version": "1"
}